djangocms_semantic_ui/__init__.py
djangocms_semantic_ui/cms_plugins.py
djangocms_semantic_ui/forms.py
djangocms_semantic_ui/models.py
djangocms_semantic_ui/migrations/0001_initial.py
djangocms_semantic_ui/migrations/0002_tab_tabcontainer.py
djangocms_semantic_ui/migrations/0003_auto_20170916_1913.py
djangocms_semantic_ui/migrations/__init__.py
djangocms_semantic_ui/templates/djangocms_semantic_ui/column.html
djangocms_semantic_ui/templates/djangocms_semantic_ui/container.html
djangocms_semantic_ui/templates/djangocms_semantic_ui/divider.html
djangocms_semantic_ui/templates/djangocms_semantic_ui/grid.html
djangocms_semantic_ui/templates/djangocms_semantic_ui/group_segment.html
djangocms_semantic_ui/templates/djangocms_semantic_ui/segment.html
djangocms_semantic_ui/templates/djangocms_semantic_ui/tab.html
djangocms_semantic_ui/templates/djangocms_semantic_ui/tab_container.html
djangocms_semantic_ui-0.1.3.2.dist-info/DESCRIPTION.rst
djangocms_semantic_ui-0.1.3.2.dist-info/METADATA
djangocms_semantic_ui-0.1.3.2.dist-info/RECORD
djangocms_semantic_ui-0.1.3.2.dist-info/WHEEL
djangocms_semantic_ui-0.1.3.2.dist-info/metadata.json
djangocms_semantic_ui-0.1.3.2.dist-info/top_level.txt
tests/__init__.py
tests/settings.py
tests/test_models.py
