Metadata-Version: 2.0
Name: djangocms-semantic-ui
Version: 0.1.3.2
Summary: Semantic UI components for django CMS
Home-page: https://github.com/CarlosMart626/djangocms_semantic_ui
Author: Carlos Martínez
Author-email: carlosmart626@gmail.com
License: MIT License
Requires-Dist: django-cms (>=3.2.0)
